{
    "set_name": "Series 2",
    "cards": [{
            "name": ["Aiden Avalon Boost"],
            "effect": ["Add 1000 to the Battle Value of Sakura and/or Tori."],
            "number": "S34",
            "rarity": "Common",
            "card_type": "Strategy"
        }, {
            "name": ["Alchemy"],
            "effect": ["Change any Clow Spirit card type to Gold for this turn only."],
            "number": "S32",
            "rarity": "Uncommon",
            "card_type": "Strategy"
        }, {
            "name": ["Burning Drain"],
            "effect": ["Subtract 2000 from the Battle Value of Wood-, Fire-, and/or Electricity-type Capture cards"],
            "number": "S40",
            "rarity": "Common",
            "card_type": "Strategy"
        }, {
            "name": ["Cereberos Arrives!"],
            "effect": ["Add 4000 to your Battle Value."],
            "number": "S37",
            "rarity": "Rare",
            "card_type": "Strategy"
        }, {
            "name": ["Clow Reed Drain"],
            "effect": ["Subract 1000 from the Battle Value of any Capture card that is not Sakura or Li Showron."],
            "number": "S41",
            "rarity": "Common",
            "card_type": "Strategy"
        }, {
            "name": ["Flaming Boost"],
            "effect": ["Add 2000 to the Battle Value of Wood-, Fire-, and/or Electricity-type Capture cards."],
            "number": "S36",
            "rarity": "Common",
            "card_type": "Strategy"
        }, {
            "name": ["Fluid Drain"],
            "effect": ["Subtract 3000 from the Battle Value of Water-, Rain-, and/or Clouds-type Capture cards."],
            "number": "S39",
            "rarity": "Rare",
            "card_type": "Strategy"
        }, {
            "name": ["Julian"],
            "effect": ["[Character type: Non-magical]"],
            "number": "C83",
            "rarity": "Uncommon",
            "card_type": "Capture",
            "element": "Gold/Electricity",
            "attack": "3000"
        }, {
            "name": ["Julian"],
            "effect": ["[Character type: Non-magical]"],
            "number": "C84",
            "rarity": "Uncommon",
            "card_type": "Capture",
            "element": "Earth/Water",
            "attack": "3000"
        }, {
            "name": ["Julian"],
            "effect": ["[Character type: Non-magical]"],
            "number": "C85",
            "rarity": "Rare",
            "card_type": "Capture",
            "element": "Clouds/Rain",
            "attack": "5000"
        }, {
            "name": ["Kero"],
            "effect": ["[Character type: Magical] "],
            "number": "C71",
            "rarity": "Common",
            "card_type": "Capture",
            "element": "Clouds/Water",
            "attack": "2000"
        }, {
            "name": ["Kero"],
            "effect": ["[Character type: Magical] "],
            "number": "C72",
            "rarity": "Rare",
            "card_type": "Capture",
            "element": "Clouds",
            "attack": "5000"
        }, {
            "name": ["Kero"],
            "effect": ["[Character type: Magical]"],
            "number": "C73",
            "rarity": "Uncommon",
            "card_type": "Capture",
            "element": "Earth/Wind",
            "attack": "3000"
        }, {
            "name": ["Kero"],
            "effect": ["[Character type: Magical] "],
            "number": "C74",
            "rarity": "Common",
            "card_type": "Capture",
            "element": "Gold/Rain",
            "attack": "5000"
        }, {
            "name": ["Kero"],
            "effect": ["[Character type: Magical] "],
            "number": "C75",
            "rarity": "Common",
            "card_type": "Capture",
            "element": "Rain/Water",
            "attack": "2000"
        }, {
            "name": ["Kero"],
            "effect": ["[Character type: Magical] "],
            "number": "C76",
            "rarity": "Common",
            "card_type": "Capture",
            "element": "Clouds/Earth",
            "attack": "3000"
        }, {
            "name": ["Kero"],
            "effect": ["[Character type: Magical]"],
            "number": "R15",
            "rarity": "Common",
            "card_type": "Reinforcement"
        }, {
            "name": ["Layla Mackenzie"],
            "effect": ["[Character type: Magical] "],
            "number": "C44",
            "rarity": "Uncommon",
            "card_type": "Capture",
            "element": "Clouds/Wind",
            "attack": "3000"
        }, {
            "name": ["Layla Mackenzie"],
            "effect": ["[Character type: Magical] "],
            "number": "C45",
            "rarity": "Uncommon",
            "card_type": "Capture",
            "element": "Fire/Rain",
            "attack": "3000"
        }, {
            "name": ["Layla Mackenzie"],
            "effect": ["[Character type: Magical] "],
            "number": "C46",
            "rarity": "Rare",
            "card_type": "Capture",
            "element": "Earth/Wind",
            "attack": "5000"
        }, {
            "name": ["Layla Mackenzie"],
            "effect": ["[Character type: Magical] "],
            "number": "C47",
            "rarity": "Uncommon",
            "card_type": "Capture",
            "element": "Electricity/Water",
            "attack": "3000"
        }, {
            "name": ["Layla Mackenzie"],
            "effect": ["[Character type: Magical] "],
            "number": "C48",
            "rarity": "Common",
            "card_type": "Capture",
            "element": "Gold/Water",
            "attack": "2000"
        }, {
            "name": ["Layla Mackenzie"],
            "effect": ["[Character type: Magical] "],
            "number": "C49",
            "rarity": "Uncommon",
            "card_type": "Capture",
            "element": "Clouds/Electricity",
            "attack": "4000"
        }, {
            "name": ["Layla Mackenzie"],
            "effect": ["[Character type: Magical] "],
            "number": "C50",
            "rarity": "Common",
            "card_type": "Capture",
            "element": "Rain/Wood",
            "attack": "2000"
        }, {
            "name": ["Layla Mackenzie"],
            "effect": ["[Character type: Magical] "],
            "number": "C51",
            "rarity": "Uncommon",
            "card_type": "Capture",
            "element": "Earth/Wind",
            "attack": "4000"
        }, {
            "name": ["Layla Mackenzie"],
            "effect": ["[Character type: Magical] "],
            "number": "C52",
            "rarity": "Rare",
            "card_type": "Capture",
            "element": "Fire/Gold",
            "attack": "5000"
        }, {
            "name": ["Layla Mackenzie"],
            "effect": ["[Character type: Magical] "],
            "number": "R12",
            "rarity": "Common",
            "card_type": "Reinforcement"
        }, {
            "name": ["Layla Mackenzie/Tori"],
            "effect": ["[Character type: Magical/Skilled]"],
            "number": "R13",
            "rarity": "Uncommon",
            "card_type": "Reinforcement"
        }, {
            "name": ["Li Showron"],
            "effect": ["[Character type: Magical] "],
            "number": "C65",
            "rarity": "Uncommon",
            "card_type": "Capture",
            "element": "Rain",
            "attack": "4000"
        }, {
            "name": ["Li Showron"],
            "effect": ["[Character type: Magical]"],
            "number": "C66",
            "rarity": "Common",
            "card_type": "Capture",
            "element": "Clouds/Rain",
            "attack": "2000"
        }, {
            "name": ["Li Showron"],
            "effect": ["[Character type: Magical]"],
            "number": "C67",
            "rarity": "Uncommon",
            "card_type": "Capture",
            "element": "Earth/Water",
            "attack": "4000"
        }, {
            "name": ["Li Showron"],
            "effect": ["[Character type: Magical] "],
            "number": "C68",
            "rarity": "Rare",
            "card_type": "Capture",
            "element": "Earth/Gold",
            "attack": "5000"
        }, {
            "name": ["Li Showron"],
            "effect": ["[Character type: Magical]"],
            "number": "C69",
            "rarity": "Common",
            "card_type": "Capture",
            "element": "Earth/Clouds",
            "attack": "2000"
        }, {
            "name": ["Li Showron"],
            "effect": ["[Character type: Magical]"],
            "number": "C70",
            "rarity": "Uncommon",
            "card_type": "Capture",
            "element": "Rain/Water",
            "attack": "3000"
        }, {
            "name": ["Li Showron's Board"],
            "effect": ["Play on Li Showron Capture or Reinforcement card. No Strategy cards may be used against him his turn."],
            "number": "S30",
            "rarity": "Rare",
            "card_type": "Strategy"
        }, {
            "name": ["Liquid Boost"],
            "effect": ["Add 3000 to the Battle Value of Water-, Rain-, and/or Clouds-type Capture cards."],
            "number": "S35",
            "rarity": "Rare",
            "card_type": "Strategy"
        }, {
            "name": ["Madison"],
            "effect": ["[Character type: Non-magical]"],
            "number": "C59",
            "rarity": "Uncommon",
            "card_type": "Capture",
            "element": "Clouds/Wood",
            "attack": "4000"
        }, {
            "name": ["Madison"],
            "effect": ["[Character type: Non-magical]"],
            "number": "C60",
            "rarity": "Common",
            "card_type": "Capture",
            "element": "Fire/Rain",
            "attack": "2000"
        }, {
            "name": ["Madison"],
            "effect": ["[Character type: Non-magical]"],
            "number": "C61",
            "rarity": "Uncommon",
            "card_type": "Capture",
            "element": "Earth/Electricity",
            "attack": "3000"
        }, {
            "name": ["Madison"],
            "effect": ["[Character type: Non-magical]"],
            "number": "C62",
            "rarity": "Uncommon",
            "card_type": "Capture",
            "element": "Gold/Water",
            "attack": "4000"
        }, {
            "name": ["Madison"],
            "effect": ["[Character type: Non-magical]"],
            "number": "C63",
            "rarity": "Rare",
            "card_type": "Capture",
            "element": "Earth/Water",
            "attack": "5000"
        }, {
            "name": ["Madison"],
            "effect": ["[Character type: Non-magical]"],
            "number": "C64",
            "rarity": "Uncommon",
            "card_type": "Capture",
            "element": "Clouds/Rain",
            "attack": "3000"
        }, {
            "name": ["Madison/Meilin"],
            "effect": ["[Character type: Nonmagical / Skilled]"],
            "number": "R14",
            "rarity": "Rare",
            "card_type": "Reinforcement"
        }, {
            "name": ["Meilin"],
            "effect": ["[Character type: Skilled]"],
            "number": "C77",
            "rarity": "Uncommon",
            "card_type": "Capture",
            "element": "Clouds/Water",
            "attack": "4000"
        }, {
            "name": ["Meilin"],
            "effect": ["[Character type: Skilled]"],
            "number": "C78",
            "rarity": "Common",
            "card_type": "Capture",
            "element": "Earth",
            "attack": "2000"
        }, {
            "name": ["Meilin"],
            "effect": ["[Character type: Skilled]"],
            "number": "C79",
            "rarity": "Uncommon",
            "card_type": "Capture",
            "element": "Rain/Wind",
            "attack": "4000"
        }, {
            "name": ["Meilin"],
            "effect": ["[Character type: Skilled]"],
            "number": "C80",
            "rarity": "Common",
            "card_type": "Capture",
            "element": "Clouds/Gold",
            "attack": "2000"
        }, {
            "name": ["Meilin"],
            "effect": ["[Character type: Skilled]"],
            "number": "C81",
            "rarity": "Uncommon",
            "card_type": "Capture",
            "element": "Clouds/Rain",
            "attack": "3000"
        }, {
            "name": ["Meilin"],
            "effect": ["[Character type: Skilled]"],
            "number": "C82",
            "rarity": "Rare",
            "card_type": "Capture",
            "element": "Earth/Water",
            "attack": "5000"
        }, {
            "name": ["Sakura"],
            "effect": ["[Character type: Magical] "],
            "number": "C53",
            "rarity": "Rare",
            "card_type": "Capture",
            "element": "Rain/Water",
            "attack": "5000"
        }, {
            "name": ["Sakura"],
            "effect": ["[Character type: Magical] "],
            "number": "C54",
            "rarity": "Common",
            "card_type": "Capture",
            "element": "Earth/Water",
            "attack": "2000"
        }, {
            "name": ["Sakura"],
            "effect": ["[Character type: Magical] "],
            "number": "C55",
            "rarity": "Common",
            "card_type": "Capture",
            "element": "Fire/Rain",
            "attack": "2000"
        }, {
            "name": ["Sakura"],
            "effect": ["[Character type: Magical] "],
            "number": "C56",
            "rarity": "Uncommon",
            "card_type": "Capture",
            "element": "Clouds/Gold",
            "attack": "4000"
        }, {
            "name": ["Sakura"],
            "effect": ["[Character type: Magical] "],
            "number": "C57",
            "rarity": "Uncommon",
            "card_type": "Capture",
            "element": "Clouds/Water",
            "attack": "3000"
        }, {
            "name": ["Sakura"],
            "effect": ["[Character type: Magical] "],
            "number": "C58",
            "rarity": "Uncommon",
            "card_type": "Capture",
            "element": "Earth/Rain",
            "attack": "4000"
        }, {
            "name": ["Sealing Wand"],
            "effect": ["Play on Sakura Capture or Reinforcement card. No Strategy cards may be used against her this turn."],
            "number": "S29",
            "rarity": "Rare",
            "card_type": "Strategy"
        }, {
            "name": ["Security Breach"],
            "effect": ["Play at any time to see your opponent's hand."],
            "number": "S28",
            "rarity": "Rare",
            "card_type": "Strategy"
        }, {
            "name": ["Shifting States"],
            "effect": ["Change the type of a Capture Card from Rain to Wood and vice-versa."],
            "number": "S26",
            "rarity": "Common",
            "card_type": "Strategy"]
    },
    {
        "name": ["Stormy Skies"],
        "effect": ["Change the type of a Capture Card from Clouds to Electricity and vice-versa."],
        "number": "S27",
        "rarity": "Common",
        "card_type": "Strategy"]
}, {
    "name": ["Sunny Skies"],
    "effect": ["Block the capture of a type Clouds or Rain Clow Spirit card for this turn."],
    "number": "S31",
    "rarity": "Uncommon",
    "card_type": "Strategy"]
}, {
    "name": ["The Bubbles"],
    "effect": [""],
    "number": "CS44",
    "rarity": "Common",
    "card_type": "Clow",
    "element": "Rain"
}, {
    "name": ["The Clouds"],
    "effect": [""],
    "number": "CS47",
    "rarity": "Rare",
    "card_type": "Clow",
    "element": "Clouds"
}, {
    "name": ["The Create"],
    "effect": [""],
    "number": "CS32",
    "rarity": "Common",
    "card_type": "Clow",
    "element": "Water"
}, {
    "name": ["The Dark"],
    "effect": [""],
    "number": "CS48",
    "rarity": "Rare",
    "card_type": "Clow",
    "element": "Clouds"
}, {
    "name": ["The Earthy"],
    "effect": ["[Major Clow Spirit]"],
    "number": "CS35",
    "rarity": "Rare",
    "card_type": "Clow",
    "element": "Earth"
}, {
    "name": ["The Float"],
    "effect": [""],
    "number": "CS49",
    "rarity": "Uncommon",
    "card_type": "Clow",
    "element": "Clouds"
}, {
    "name": ["The Fly"],
    "effect": [""],
    "number": "CS52",
    "rarity": "Rare",
    "card_type": "Clow",
    "element": "Clouds"
}, {
    "name": ["The Illusion"],
    "effect": [""],
    "number": "CS38",
    "rarity": "Common",
    "card_type": "Clow",
    "element": "Earth"
}, {
    "name": ["The Libra"],
    "effect": [""],
    "number": "CS33",
    "rarity": "Common",
    "card_type": "Clow",
    "element": "Water"
}, {
    "name": ["The Loop"],
    "effect": [""],
    "number": "CS45",
    "rarity": "Common",
    "card_type": "Clow",
    "element": "Rain"
}, {
    "name": ["The Maze"],
    "effect": [""],
    "number": "CS39",
    "rarity": "Common",
    "card_type": "Clow",
    "element": "Earth"
}, {
    "name": ["The Mist"],
    "effect": [""],
    "number": "CS50",
    "rarity": "Common",
    "card_type": "Clow",
    "element": "Clouds"
}, {
    "name": ["The Move"],
    "effect": [""],
    "number": "CS31",
    "rarity": "Uncommon",
    "card_type": "Clow",
    "element": "Water"
}, {
    "name": ["The Rain"],
    "effect": [""],
    "number": "CS41",
    "rarity": "Rare",
    "card_type": "Clow",
    "element": "Rain"
}, {
    "name": ["The Return"],
    "effect": [""],
    "number": "CS34",
    "rarity": "Rare",
    "card_type": "Clow",
    "element": "Water"
}, {
    "name": ["The Sand"],
    "effect": [""],
    "number": "CS36",
    "rarity": "Uncommon",
    "card_type": "Clow",
    "element": "Earth"
}, {
    "name": ["The Shot"],
    "effect": [""],
    "number": "CS40",
    "rarity": "Rare",
    "card_type": "Clow",
    "element": "Earth"
}, {
    "name": ["The Silent"],
    "effect": [""],
    "number": "CS51",
    "rarity": "Common",
    "card_type": "Clow",
    "element": "Clouds"
}, {
    "name": ["The Snow"],
    "effect": [""],
    "number": "CS46",
    "rarity": "Rare",
    "card_type": "Clow",
    "element": "Rain"
}, {
    "name": ["The Storm"],
    "effect": [""],
    "number": "CS42",
    "rarity": "Rare",
    "card_type": "Clow",
    "element": "Rain"
}, {
    "name": ["The Through"],
    "effect": [""],
    "number": "CS43",
    "rarity": "Uncommon",
    "card_type": "Clow",
    "element": "Rain"
}, {
    "name": ["The Twin"],
    "effect": [""],
    "number": "CS37",
    "rarity": "Rare",
    "card_type": "Clow",
    "element": "Earth"
}, {
    "name": ["The Watery"],
    "effect": ["[Major Clow Spirit]"],
    "number": "CS29",
    "rarity": "Rare",
    "card_type": "Clow",
    "element": "Water"
}, {
    "name": ["The Wave"],
    "effect": [""],
    "number": "CS30",
    "rarity": "Rare",
    "card_type": "Clow",
    "element": "Water"
}, {
    "name": ["Tie Breaker Drain"],
    "effect": ["Subtract 500 from your opopnent's Battle Value."],
    "number": "S33",
    "rarity": "Common",
    "card_type": "Strategy"
}, {
    "name": ["Tori"],
    "effect": ["[Character type: Skilled]"],
    "number": "C86",
    "rarity": "Rare",
    "card_type": "Capture",
    "element": "Clouds/Wood",
    "attack": "5000"
}, {
    "name": ["Tori"],
    "effect": ["[Character type: Skilled]"],
    "number": "C87",
    "rarity": "Uncommon",
    "card_type": "Capture",
    "element": "Earth/Rain",
    "attack": "4000"
}, {
    "name": ["Tori"],
    "effect": ["[Character type: Skilled]"],
    "number": "C88",
    "rarity": "Uncommon",
    "card_type": "Capture",
    "element": "Gold/Water",
    "attack": "3000"
}, {
    "name": ["Use the Clow"],
    "effect": ["Attach to a captured Clow Spirit card. The card is a Major Clow Spirit for this turn only."],
    "number": "S25",
    "rarity": "Rare",
    "card_type": "Strategy"
}, {
    "name": ["Yue's Judgement"],
    "effect": ["Subtract 4000 from your opponent's Battle Value."],
    "number": "S38",
    "rarity": "Rare",
    "card_type": "Strategy"
}]
}